pygena/__init__.py
pygena/base.py
pygena/examples/__init__.py
pygena/examples/knapsack.py
pygena/examples/sum.py
pygena/examples/text.py
pygena-0.2.0.dist-info/LICENSE
pygena-0.2.0.dist-info/METADATA
pygena-0.2.0.dist-info/WHEEL
pygena-0.2.0.dist-info/top_level.txt
pygena-0.2.0.dist-info/RECORD
