Metadata-Version: 2.1
Name: pygena
Version: 0.2.0
Summary: A simple genetic algorithm library in Python.
Home-page: https://github.com/atasoglu/pygena
Author: Ahmet Atasoglu
Author-email: ahmetatasoglu98@gmail.com
License: MIT
Classifier: Programming Language :: Python :: 3
Classifier: License :: OSI Approved :: MIT License
Classifier: Operating System :: OS Independent
Requires-Python: >=3.7
License-File: LICENSE
